{
	"$schema": "http://schema.management.azure.com/schemas/2015-01-01/deploymentTemplate.json#",
	"contentVersion": "1.0.0.0",
	"parameters": {
		"factoryName": {
			"type": "string",
			"metadata": "Data Factory name",
			"defaultValue": "mohamedAD1"
		}
	},
	"variables": {
		"factoryId": "[concat('Microsoft.DataFactory/factories/', parameters('factoryName'))]"
	},
	"resources": [
		{
			"name": "[concat(parameters('factoryName'), '/Parquet4')]",
			"type": "Microsoft.DataFactory/factories/datasets",
			"apiVersion": "2018-06-01",
			"properties": {
				"linkedServiceName": {
					"referenceName": "ADLS2",
					"type": "LinkedServiceReference"
				},
				"parameters": {
					"tablename": {
						"type": "string"
					},
					"tablecatalogname": {
						"type": "string"
					}
				},
				"annotations": [],
				"type": "Parquet",
				"typeProperties": {
					"location": {
						"type": "AzureBlobFSLocation",
						"fileSystem": "address"
					},
					"compressionCodec": "snappy"
				},
				"schema": []
			},
			"dependsOn": []
		},
		{
			"name": "[concat(parameters('factoryName'), '/Parts_Inventorytransactions')]",
			"type": "Microsoft.DataFactory/factories/datasets",
			"apiVersion": "2018-06-01",
			"properties": {
				"linkedServiceName": {
					"referenceName": "ABLBMohamedBlob2",
					"type": "LinkedServiceReference"
				},
				"annotations": [],
				"type": "Excel",
				"typeProperties": {
					"sheetName": "TRANSACTIONS",
					"location": {
						"type": "AzureBlobStorageLocation",
						"fileName": "Parts_Inventory_Transactions_20210105151858.xlsx",
						"container": "inventory"
					},
					"firstRowAsHeader": true
				},
				"schema": [
					{
						"name": "ITEM_NUMBER",
						"type": "String"
					},
					{
						"name": "ORGANIZATION_CODE",
						"type": "String"
					},
					{
						"name": "SUBINVENTORY_NAME",
						"type": "String"
					},
					{
						"name": "TRANSACTION_QUANTITY",
						"type": "String"
					},
					{
						"name": "TRANSACTION_DATE",
						"type": "String"
					},
					{
						"name": "TRANSACTION_REFERENCE",
						"type": "String"
					},
					{
						"name": "LOCATOR_NAME",
						"type": "String"
					},
					{
						"name": "TRANSACTION_COST",
						"type": "String"
					},
					{
						"name": "FM_SERIAL_NUMBER",
						"type": "String"
					},
					{
						"name": "TO_SERIAL_NUMBER",
						"type": "String"
					},
					{
						"name": "Distribution_Account",
						"type": "String"
					},
					{
						"name": "ORG_NAME",
						"type": "String"
					},
					{
						"name": "PE_EXT_ATTRIBUTE1",
						"type": "String"
					},
					{
						"name": "PE_EXT_ATTRIBUTE2",
						"type": "String"
					}
				]
			},
			"dependsOn": []
		},
		{
			"name": "[concat(parameters('factoryName'), '/Parts_Item_Category_Assignment')]",
			"type": "Microsoft.DataFactory/factories/datasets",
			"apiVersion": "2018-06-01",
			"properties": {
				"linkedServiceName": {
					"referenceName": "ABLBMohamedBlob2",
					"type": "LinkedServiceReference"
				},
				"annotations": [],
				"type": "Excel",
				"typeProperties": {
					"sheetName": "Sheet1",
					"location": {
						"type": "AzureBlobStorageLocation",
						"fileName": "Parts_Item_Category_Assignment_20210105151430.xlsx",
						"container": "inventory"
					},
					"firstRowAsHeader": true
				},
				"schema": []
			},
			"dependsOn": []
		},
		{
			"name": "[concat(parameters('factoryName'), '/Parts_Item_Cross_Reference')]",
			"type": "Microsoft.DataFactory/factories/datasets",
			"apiVersion": "2018-06-01",
			"properties": {
				"linkedServiceName": {
					"referenceName": "ABLBMohamedBlob2",
					"type": "LinkedServiceReference"
				},
				"annotations": [],
				"type": "Excel",
				"typeProperties": {
					"sheetName": "Sheet1",
					"location": {
						"type": "AzureBlobStorageLocation",
						"fileName": "Parts_Item_Cross_Reference_20210105151523.xlsx",
						"container": "inventory"
					},
					"firstRowAsHeader": true
				},
				"schema": [
					{
						"name": "ITEM_NUMBER",
						"type": "String"
					},
					{
						"name": "CROSS_REFERENCE_TYPE",
						"type": "String"
					},
					{
						"name": "CROSS_REFERENCE",
						"type": "String"
					},
					{
						"name": "DESCRIPTION",
						"type": "String"
					},
					{
						"name": "ORGANIZATION_CODE",
						"type": "String"
					},
					{
						"name": "ORG_NAME",
						"type": "String"
					}
				]
			},
			"dependsOn": []
		},
		{
			"name": "[concat(parameters('factoryName'), '/Parts_Item_Header')]",
			"type": "Microsoft.DataFactory/factories/datasets",
			"apiVersion": "2018-06-01",
			"properties": {
				"linkedServiceName": {
					"referenceName": "ABLBMohamedBlob2",
					"type": "LinkedServiceReference"
				},
				"annotations": [],
				"type": "Excel",
				"typeProperties": {
					"sheetName": "Sheet1",
					"location": {
						"type": "AzureBlobStorageLocation",
						"fileName": "Parts_Item_Header_20210105151306.xlsx",
						"container": "inventory"
					},
					"firstRowAsHeader": true
				},
				"schema": [
					{
						"name": "ITEM_NUMBER",
						"type": "String"
					},
					{
						"name": "DESCRIPTION",
						"type": "String"
					},
					{
						"name": "DESCRIPTION_ESA",
						"type": "String"
					},
					{
						"name": "ORANIZATION_CODE",
						"type": "String"
					},
					{
						"name": "TEMPLATE_NAME",
						"type": "String"
					},
					{
						"name": "LIST_PRICE_PER_UNIT",
						"type": "String"
					},
					{
						"name": "UOM_CODE",
						"type": "String"
					},
					{
						"name": "WEIGHT_UOM_CODE",
						"type": "String"
					},
					{
						"name": "UNIT_WEIGHT",
						"type": "String"
					},
					{
						"name": "VOLUME_UOM_CODE",
						"type": "String"
					},
					{
						"name": "UNIT_VOLUME",
						"type": "String"
					},
					{
						"name": "MIN_MINMAX_QUANTITY",
						"type": "String"
					},
					{
						"name": "MAX_MINMAX_QUANTITY",
						"type": "String"
					},
					{
						"name": "FULL_LEAD_TIME",
						"type": "String"
					},
					{
						"name": "FIXED_LOT_MULTIPLIER",
						"type": "String"
					},
					{
						"name": "FIXED_ORDER_QUANTITY",
						"type": "String"
					},
					{
						"name": "MINIMUM_ORDER_QUANTITY",
						"type": "String"
					},
					{
						"name": "MAXIMUM_ORDER_QUANTITY",
						"type": "String"
					},
					{
						"name": "LONG_DESCRIPTION",
						"type": "String"
					},
					{
						"name": "ITEM_INV_APPLICATION",
						"type": "String"
					},
					{
						"name": "TRANSACTION_CONDITION_CODE",
						"type": "String"
					},
					{
						"name": "ADJUSTMENT_ACCOUNT",
						"type": "String"
					},
					{
						"name": "CORRECTION_ACCOUNT",
						"type": "String"
					},
					{
						"name": "SALES_COST_ACCOUNT",
						"type": "String"
					},
					{
						"name": "FOUR_DIGIT_CODE",
						"type": "String"
					},
					{
						"name": "ORG_NAME",
						"type": "String"
					},
					{
						"name": "PE_EXT_ATTRIBUTE1",
						"type": "String"
					},
					{
						"name": "PE_EXT_ATTRIBUTE2",
						"type": "String"
					}
				]
			},
			"dependsOn": []
		},
		{
			"name": "[concat(parameters('factoryName'), '/Parts_Item_Transaction_Default_Locators')]",
			"type": "Microsoft.DataFactory/factories/datasets",
			"apiVersion": "2018-06-01",
			"properties": {
				"linkedServiceName": {
					"referenceName": "ABLBMohamedBlob2",
					"type": "LinkedServiceReference"
				},
				"annotations": [],
				"type": "Excel",
				"typeProperties": {
					"sheetName": "Sheet1",
					"location": {
						"type": "AzureBlobStorageLocation",
						"folderPath": "Transaction_Default_Locators",
						"container": "inventory"
					},
					"firstRowAsHeader": true
				},
				"schema": [
					{
						"name": "ITEM_NUMBER",
						"type": "String"
					},
					{
						"name": "ORGANIZATION_CODE",
						"type": "String"
					},
					{
						"name": "SUBINVENTORY_NAME",
						"type": "String"
					},
					{
						"name": "LOCATOR_NAME",
						"type": "String"
					},
					{
						"name": "ORG_NAME",
						"type": "String"
					}
				]
			},
			"dependsOn": []
		},
		{
			"name": "[concat(parameters('factoryName'), '/Parts_Item_Transaction_Default_Subinv')]",
			"type": "Microsoft.DataFactory/factories/datasets",
			"apiVersion": "2018-06-01",
			"properties": {
				"linkedServiceName": {
					"referenceName": "ADLS2",
					"type": "LinkedServiceReference"
				},
				"annotations": [],
				"type": "DelimitedText",
				"typeProperties": {
					"location": {
						"type": "AzureBlobFSLocation",
						"fileSystem": "inventoryoutput"
					},
					"columnDelimiter": "|",
					"escapeChar": "\\",
					"firstRowAsHeader": true,
					"quoteChar": "\""
				},
				"schema": [
					{
						"name": "ITEM_NUMBER",
						"type": "String"
					},
					{
						"name": "ORGANIZATION_CODE",
						"type": "String"
					},
					{
						"name": "SUBINVENTORY_NAME",
						"type": "String"
					},
					{
						"name": "ORG_NAME",
						"type": "String"
					}
				]
			},
			"dependsOn": []
		},
		{
			"name": "[concat(parameters('factoryName'), '/Parts_Item_Transaction_Default_Subinventories')]",
			"type": "Microsoft.DataFactory/factories/datasets",
			"apiVersion": "2018-06-01",
			"properties": {
				"linkedServiceName": {
					"referenceName": "ABLBMohamedBlob2",
					"type": "LinkedServiceReference"
				},
				"annotations": [],
				"type": "Excel",
				"typeProperties": {
					"sheetName": "Sheet1",
					"location": {
						"type": "AzureBlobStorageLocation",
						"fileName": "Parts_Item_Transaction_Default_Subinventories_20210105151805.xlsx",
						"container": "inventory"
					},
					"firstRowAsHeader": true
				},
				"schema": [
					{
						"name": "ITEM_NUMBER",
						"type": "String"
					},
					{
						"name": "ORGANIZATION_CODE",
						"type": "String"
					},
					{
						"name": "SUBINVENTORY_NAME",
						"type": "String"
					},
					{
						"name": "ORG_NAME",
						"type": "String"
					}
				]
			},
			"dependsOn": []
		},
		{
			"name": "[concat(parameters('factoryName'), '/SourceDataset_gv3')]",
			"type": "Microsoft.DataFactory/factories/datasets",
			"apiVersion": "2018-06-01",
			"properties": {
				"linkedServiceName": {
					"referenceName": "ABLBMohamedBlob2",
					"type": "LinkedServiceReference"
				},
				"annotations": [],
				"type": "DelimitedText",
				"typeProperties": {
					"location": {
						"type": "AzureBlobStorageLocation",
						"fileName": "TopMovies_Part1.csv",
						"container": "csvfiles"
					},
					"columnDelimiter": ";",
					"escapeChar": "\\",
					"firstRowAsHeader": true,
					"quoteChar": "\""
				},
				"schema": [
					{
						"name": "Index",
						"type": "String"
					},
					{
						"name": "MovieTitle",
						"type": "String"
					}
				]
			},
			"dependsOn": []
		},
		{
			"name": "[concat(parameters('factoryName'), '/SourceDataset_s88')]",
			"type": "Microsoft.DataFactory/factories/datasets",
			"apiVersion": "2018-06-01",
			"properties": {
				"linkedServiceName": {
					"referenceName": "ABLBMohamedBlob2",
					"type": "LinkedServiceReference"
				},
				"annotations": [],
				"type": "DelimitedText",
				"typeProperties": {
					"location": {
						"type": "AzureBlobStorageLocation",
						"container": "csvfiles"
					},
					"columnDelimiter": ";",
					"escapeChar": "\\",
					"firstRowAsHeader": true,
					"quoteChar": "\""
				},
				"schema": [
					{
						"name": "Index",
						"type": "String"
					},
					{
						"name": "MovieTitle",
						"type": "String"
					}
				]
			},
			"dependsOn": []
		},
		{
			"name": "[concat(parameters('factoryName'), '/SqlIdentification')]",
			"type": "Microsoft.DataFactory/factories/datasets",
			"apiVersion": "2018-06-01",
			"properties": {
				"linkedServiceName": {
					"referenceName": "AzureSqlDatabase1",
					"type": "LinkedServiceReference"
				},
				"annotations": [],
				"type": "AzureSqlTable",
				"schema": [
					{
						"name": "UnitId FK",
						"type": "int",
						"precision": 10
					},
					{
						"name": "Unit_GovernmentID",
						"type": "varchar"
					},
					{
						"name": "Unit_NickName",
						"type": "varchar"
					},
					{
						"name": "Customer_BillingReference",
						"type": "varchar"
					},
					{
						"name": "Unit_DownInd",
						"type": "varchar"
					},
					{
						"name": "Unit_RegisteredNo",
						"type": "varchar"
					},
					{
						"name": "Unit_MfgYear",
						"type": "varchar"
					},
					{
						"name": "Unit_WarrantyStartDate",
						"type": "varchar"
					},
					{
						"name": "Unit_WarrantyEndDate",
						"type": "varchar"
					},
					{
						"name": "Unit_InstallDate",
						"type": "varchar"
					},
					{
						"name": "Unit_HandoverDate",
						"type": "varchar"
					},
					{
						"name": "AnnualSafetyTest_LastInspectionDate",
						"type": "varchar"
					},
					{
						"name": "Unit_JobNo",
						"type": "varchar"
					},
					{
						"name": "Unit_FactorySerialNo",
						"type": "varchar"
					},
					{
						"name": "Unit_Smart_ViewID",
						"type": "varchar"
					},
					{
						"name": "Unit_Smart_ExternalID",
						"type": "varchar"
					},
					{
						"name": "Unit_Smart_InstallationDate",
						"type": "varchar"
					},
					{
						"name": "Unit_SmartMAX_ViewID",
						"type": "varchar"
					},
					{
						"name": "Unit_SmartMAX_ExternalID",
						"type": "varchar"
					},
					{
						"name": "ID",
						"type": "int",
						"precision": 10
					}
				],
				"typeProperties": {
					"schema": "unit",
					"table": "Identification"
				}
			},
			"dependsOn": []
		},
		{
			"name": "[concat(parameters('factoryName'), '/Viewbuilding_API_addtest')]",
			"type": "Microsoft.DataFactory/factories/datasets",
			"apiVersion": "2018-06-01",
			"properties": {
				"linkedServiceName": {
					"referenceName": "AzureSqlDatabase1",
					"type": "LinkedServiceReference"
				},
				"annotations": [],
				"type": "AzureSqlTable",
				"schema": [
					{
						"name": "buildingCode",
						"type": "nvarchar"
					},
					{
						"name": "Data",
						"type": "nvarchar"
					},
					{
						"name": "HashKey",
						"type": "varbinary"
					},
					{
						"name": "ETL_Load_Date_Time",
						"type": "datetime",
						"precision": 23,
						"scale": 3
					}
				],
				"typeProperties": {
					"schema": "building",
					"table": "Viewbuilding_API_addtest"
				}
			},
			"dependsOn": []
		},
		{
			"name": "[concat(parameters('factoryName'), '/address')]",
			"type": "Microsoft.DataFactory/factories/datasets",
			"apiVersion": "2018-06-01",
			"properties": {
				"linkedServiceName": {
					"referenceName": "AzureBlobStorage1",
					"type": "LinkedServiceReference"
				},
				"annotations": [],
				"type": "Excel",
				"typeProperties": {
					"sheetName": "Sheet1",
					"location": {
						"type": "AzureBlobStorageLocation",
						"fileName": "ORA_FD02_CustomerAddress20201005165901.xlsx",
						"container": "address"
					},
					"firstRowAsHeader": true
				},
				"schema": [
					{
						"name": "Customer Name",
						"type": "String"
					},
					{
						"name": "Customer Header Reference",
						"type": "String"
					},
					{
						"name": "Address Reference",
						"type": "String"
					},
					{
						"name": "Site Use Code",
						"type": "String"
					},
					{
						"name": "Primary Site Use Flag",
						"type": "String"
					},
					{
						"name": " Location",
						"type": "String"
					},
					{
						"name": "Bill To Orig Address Reference",
						"type": "String"
					},
					{
						"name": "Address Line 1",
						"type": "String"
					},
					{
						"name": "Address Line 2",
						"type": "String"
					},
					{
						"name": "Address Line 3",
						"type": "String"
					},
					{
						"name": "Address Line 4",
						"type": "String"
					},
					{
						"name": "Address Lines Phonetic",
						"type": "String"
					},
					{
						"name": "City",
						"type": "String"
					},
					{
						"name": "Province",
						"type": "String"
					},
					{
						"name": "State",
						"type": "String"
					},
					{
						"name": "County",
						"type": "String"
					},
					{
						"name": "Postal Code",
						"type": "String"
					},
					{
						"name": "Country",
						"type": "String"
					},
					{
						"name": "Receivables Account",
						"type": "String"
					},
					{
						"name": "Revenue Account",
						"type": "String"
					},
					{
						"name": "Tax Account",
						"type": "String"
					},
					{
						"name": "Freight Account",
						"type": "String"
					},
					{
						"name": "Clearing Account",
						"type": "String"
					},
					{
						"name": "Unbilled Receivables Account",
						"type": "String"
					},
					{
						"name": "Unearned Revenue Account",
						"type": "String"
					},
					{
						"name": "Payment Method Name",
						"type": "String"
					},
					{
						"name": "Payment Method Primary Flag",
						"type": "String"
					},
					{
						"name": "Customer Profile",
						"type": "String"
					},
					{
						"name": "Site Use Tax Reference",
						"type": "String"
					},
					{
						"name": "Time Zone",
						"type": "String"
					},
					{
						"name": "Language",
						"type": "String"
					},
					{
						"name": "Contributor Class at Account Site",
						"type": "String"
					},
					{
						"name": "Use Cust Site Profile Flag at Account Site",
						"type": "String"
					},
					{
						"name": "Contributor Class at Account Site Use",
						"type": "String"
					},
					{
						"name": "Use Cust Site Profile Flag at Account Site Use",
						"type": "String"
					},
					{
						"name": "Economic Activity",
						"type": "String"
					},
					{
						"name": "Operating Unit Name",
						"type": "String"
					},
					{
						"name": "Payment Term Name",
						"type": "String"
					},
					{
						"name": "Concept Code (CR)",
						"type": "String"
					},
					{
						"name": "Giro (CL)",
						"type": "String"
					},
					{
						"name": "US Remit-to Address Mapping",
						"type": "String"
					},
					{
						"name": "US Tax Area Id",
						"type": "String"
					},
					{
						"name": "Union Local",
						"type": "String"
					},
					{
						"name": "TAID User Override",
						"type": "String"
					},
					{
						"name": "TAID Last Checked",
						"type": "String"
					},
					{
						"name": "TAID Assignment Result",
						"type": "String"
					},
					{
						"name": "TAID Confidence Indicator",
						"type": "String"
					},
					{
						"name": "TAID Precision",
						"type": "String"
					},
					{
						"name": "CRM Account",
						"type": "String"
					}
				]
			},
			"dependsOn": []
		},
		{
			"name": "[concat(parameters('factoryName'), '/am_da_ds_dst_exviewBuildingapi')]",
			"type": "Microsoft.DataFactory/factories/datasets",
			"apiVersion": "2018-06-01",
			"properties": {
				"linkedServiceName": {
					"referenceName": "AzureSqlDatabase1",
					"type": "LinkedServiceReference"
				},
				"annotations": [],
				"type": "AzureSqlTable",
				"schema": [
					{
						"name": "CustomerCode",
						"type": "nvarchar"
					},
					{
						"name": "Data",
						"type": "nvarchar"
					},
					{
						"name": "HashKey",
						"type": "varbinary"
					},
					{
						"name": "ETL_Load_Date_Time",
						"type": "datetime",
						"precision": 23,
						"scale": 3
					}
				],
				"typeProperties": {
					"schema": "building",
					"table": "am_da_ds_dst_exviewBuildingapi"
				}
			},
			"dependsOn": []
		},
		{
			"name": "[concat(parameters('factoryName'), '/building')]",
			"type": "Microsoft.DataFactory/factories/datasets",
			"apiVersion": "2018-06-01",
			"properties": {
				"linkedServiceName": {
					"referenceName": "AzureSqlDatabase1",
					"type": "LinkedServiceReference"
				},
				"annotations": [],
				"type": "AzureSqlTable",
				"schema": [
					{
						"name": "ExternalBuildingId",
						"type": "varchar"
					},
					{
						"name": "BuildingName_local",
						"type": "varchar"
					},
					{
						"name": "StreetAddress_Local",
						"type": "varchar"
					},
					{
						"name": "City_Local",
						"type": "varchar"
					},
					{
						"name": "Postcode",
						"type": "varchar"
					},
					{
						"name": "MainTypeViewId",
						"type": "varchar"
					},
					{
						"name": "MainTypeName_En",
						"type": "varchar"
					},
					{
						"name": "SubTypeViewId",
						"type": "varchar"
					},
					{
						"name": "SubTypeName_En",
						"type": "varchar"
					},
					{
						"name": "BuildingNo",
						"type": "varchar"
					},
					{
						"name": "CustomerNo",
						"type": "varchar"
					},
					{
						"name": "SumOfTotalUnits",
						"type": "varchar"
					},
					{
						"name": "SumOfUnitsInService",
						"type": "varchar"
					},
					{
						"name": "OfficeViewId",
						"type": "varchar"
					},
					{
						"name": "OfficeName_En",
						"type": "varchar"
					},
					{
						"name": "UnitsScheduleHours",
						"type": "varchar"
					},
					{
						"name": "UnitsScheduleHoursViewId",
						"type": "varchar"
					},
					{
						"name": "UnitsScheduleTime",
						"type": "varchar"
					},
					{
						"name": "UnitsScheduleTimeViewId",
						"type": "varchar"
					},
					{
						"name": "TargetCallRate",
						"type": "varchar"
					},
					{
						"name": "RunInfo",
						"type": "varchar"
					},
					{
						"name": "RunTypeViewId",
						"type": "varchar"
					},
					{
						"name": "RunTypeName",
						"type": "varchar"
					},
					{
						"name": "RunViewId",
						"type": "varchar"
					},
					{
						"name": "RunName",
						"type": "varchar"
					},
					{
						"name": "BHSWPResponse",
						"type": "varchar"
					},
					{
						"name": "BHStopResponse",
						"type": "varchar"
					},
					{
						"name": "BHOthersResponse",
						"type": "varchar"
					},
					{
						"name": "AHSWPResponse",
						"type": "varchar"
					},
					{
						"name": "AHStopResponse",
						"type": "varchar"
					},
					{
						"name": "AHOthersResponse",
						"type": "varchar"
					},
					{
						"name": "Notes",
						"type": "varchar"
					},
					{
						"name": "BusinessHourContactInfo",
						"type": "varchar"
					},
					{
						"name": "BHSiteContact",
						"type": "varchar"
					},
					{
						"name": "BHContactPhone1",
						"type": "varchar"
					},
					{
						"name": "BHContactMobile",
						"type": "varchar"
					},
					{
						"name": "BHContactRoleViewId",
						"type": "varchar"
					},
					{
						"name": "BHContactRoleName",
						"type": "varchar"
					},
					{
						"name": "AfterHourContactInfo",
						"type": "varchar"
					},
					{
						"name": "AHSiteContact",
						"type": "varchar"
					},
					{
						"name": "AHContactPhone1",
						"type": "varchar"
					},
					{
						"name": "AHContactMobile",
						"type": "varchar"
					},
					{
						"name": "AHContactRoleViewId",
						"type": "varchar"
					},
					{
						"name": "AHContactRoleViewName",
						"type": "varchar"
					},
					{
						"name": "State",
						"type": "varchar"
					},
					{
						"name": "ViewId",
						"type": "varchar"
					},
					{
						"name": "Name",
						"type": "varchar"
					},
					{
						"name": "TimeZone",
						"type": "varchar"
					},
					{
						"name": "CustomerCode",
						"type": "varchar"
					}
				],
				"typeProperties": {
					"schema": "dbo",
					"table": "building stg"
				}
			},
			"dependsOn": []
		},
		{
			"name": "[concat(parameters('factoryName'), '/building3')]",
			"type": "Microsoft.DataFactory/factories/datasets",
			"apiVersion": "2018-06-01",
			"properties": {
				"linkedServiceName": {
					"referenceName": "ABLBMohamedBlob2",
					"type": "LinkedServiceReference"
				},
				"annotations": [],
				"type": "Excel",
				"typeProperties": {
					"sheetName": "Sheet1",
					"location": {
						"type": "AzureBlobStorageLocation",
						"container": "building"
					},
					"firstRowAsHeader": true
				},
				"schema": []
			},
			"dependsOn": []
		},
		{
			"name": "[concat(parameters('factoryName'), '/buildingsrc')]",
			"type": "Microsoft.DataFactory/factories/datasets",
			"apiVersion": "2018-06-01",
			"properties": {
				"linkedServiceName": {
					"referenceName": "AzureBlobStorage1",
					"type": "LinkedServiceReference"
				},
				"annotations": [],
				"type": "Excel",
				"typeProperties": {
					"sheetName": "Sheet1",
					"location": {
						"type": "AzureBlobStorageLocation",
						"fileName": "View_Building_20201005094320.xlsx",
						"container": "building"
					},
					"firstRowAsHeader": true
				},
				"schema": [
					{
						"name": "ExternalBuildingId",
						"type": "String"
					},
					{
						"name": "BuildingName_local",
						"type": "String"
					},
					{
						"name": "StreetAddress_Local",
						"type": "String"
					},
					{
						"name": "City_Local",
						"type": "String"
					},
					{
						"name": "Postcode",
						"type": "String"
					},
					{
						"name": "MainTypeViewId",
						"type": "String"
					},
					{
						"name": "MainTypeName_En",
						"type": "String"
					},
					{
						"name": "SubTypeViewId",
						"type": "String"
					},
					{
						"name": "SubTypeName_En",
						"type": "String"
					},
					{
						"name": "BuildingNo",
						"type": "String"
					},
					{
						"name": "CustomerNo",
						"type": "String"
					},
					{
						"name": "SumOfTotalUnits",
						"type": "String"
					},
					{
						"name": "SumOfUnitsInService",
						"type": "String"
					},
					{
						"name": "OfficeViewId",
						"type": "String"
					},
					{
						"name": "OfficeName_En",
						"type": "String"
					},
					{
						"name": "UnitsScheduleHours",
						"type": "String"
					},
					{
						"name": "UnitsScheduleHoursViewId",
						"type": "String"
					},
					{
						"name": "UnitsScheduleTime",
						"type": "String"
					},
					{
						"name": "UnitsScheduleTimeViewId",
						"type": "String"
					},
					{
						"name": "TargetCallRate",
						"type": "String"
					},
					{
						"name": "RunInfo",
						"type": "String"
					},
					{
						"name": "RunTypeViewId",
						"type": "String"
					},
					{
						"name": "RunTypeName",
						"type": "String"
					},
					{
						"name": "RunViewId",
						"type": "String"
					},
					{
						"name": "RunName",
						"type": "String"
					},
					{
						"name": "BHSWPResponse",
						"type": "String"
					},
					{
						"name": "BHStopResponse",
						"type": "String"
					},
					{
						"name": "BHOthersResponse",
						"type": "String"
					},
					{
						"name": "AHSWPResponse",
						"type": "String"
					},
					{
						"name": "AHStopResponse",
						"type": "String"
					},
					{
						"name": "AHOthersResponse",
						"type": "String"
					},
					{
						"name": "Notes",
						"type": "String"
					},
					{
						"name": "BusinessHourContactInfo",
						"type": "String"
					},
					{
						"name": "BHSiteContact",
						"type": "String"
					},
					{
						"name": "BHContactPhone1",
						"type": "String"
					},
					{
						"name": "BHContactMobile",
						"type": "String"
					},
					{
						"name": "BHContactRoleViewId",
						"type": "String"
					},
					{
						"name": "BHContactRoleName",
						"type": "String"
					},
					{
						"name": "AfterHourContactInfo",
						"type": "String"
					},
					{
						"name": "AHSiteContact",
						"type": "String"
					},
					{
						"name": "AHContactPhone1",
						"type": "String"
					},
					{
						"name": "AHContactMobile",
						"type": "String"
					},
					{
						"name": "AHContactRoleViewId",
						"type": "String"
					},
					{
						"name": "AHContactRoleViewName",
						"type": "String"
					},
					{
						"name": "State",
						"type": "String"
					},
					{
						"name": "ViewId",
						"type": "String"
					},
					{
						"name": "Name",
						"type": "String"
					},
					{
						"name": "TimeZone",
						"type": "String"
					},
					{
						"name": "CustomerCode",
						"type": "String"
					}
				]
			},
			"dependsOn": []
		},
		{
			"name": "[concat(parameters('factoryName'), '/buildingstg')]",
			"type": "Microsoft.DataFactory/factories/datasets",
			"apiVersion": "2018-06-01",
			"properties": {
				"linkedServiceName": {
					"referenceName": "AzureSqlDatabase1",
					"type": "LinkedServiceReference"
				},
				"annotations": [],
				"type": "AzureSqlTable",
				"schema": [
					{
						"name": "ExternalBuildingId",
						"type": "varchar"
					},
					{
						"name": "BuildingName_local",
						"type": "varchar"
					},
					{
						"name": "StreetAddress_Local",
						"type": "varchar"
					},
					{
						"name": "City_Local",
						"type": "varchar"
					},
					{
						"name": "Postcode",
						"type": "varchar"
					},
					{
						"name": "MainTypeViewId",
						"type": "varchar"
					},
					{
						"name": "MainTypeName_En",
						"type": "varchar"
					},
					{
						"name": "SubTypeViewId",
						"type": "varchar"
					},
					{
						"name": "SubTypeName_En",
						"type": "varchar"
					},
					{
						"name": "BuildingNo",
						"type": "varchar"
					},
					{
						"name": "CustomerNo",
						"type": "varchar"
					},
					{
						"name": "SumOfTotalUnits",
						"type": "varchar"
					},
					{
						"name": "SumOfUnitsInService",
						"type": "varchar"
					},
					{
						"name": "OfficeViewId",
						"type": "varchar"
					},
					{
						"name": "OfficeName_En",
						"type": "varchar"
					},
					{
						"name": "UnitsScheduleHours",
						"type": "varchar"
					},
					{
						"name": "UnitsScheduleHoursViewId",
						"type": "varchar"
					},
					{
						"name": "UnitsScheduleTime",
						"type": "varchar"
					},
					{
						"name": "UnitsScheduleTimeViewId",
						"type": "varchar"
					},
					{
						"name": "TargetCallRate",
						"type": "varchar"
					},
					{
						"name": "RunInfo",
						"type": "varchar"
					},
					{
						"name": "RunTypeViewId",
						"type": "varchar"
					},
					{
						"name": "RunTypeName",
						"type": "varchar"
					},
					{
						"name": "RunViewId",
						"type": "varchar"
					},
					{
						"name": "RunName",
						"type": "varchar"
					},
					{
						"name": "BHSWPResponse",
						"type": "varchar"
					},
					{
						"name": "BHStopResponse",
						"type": "varchar"
					},
					{
						"name": "BHOthersResponse",
						"type": "varchar"
					},
					{
						"name": "AHSWPResponse",
						"type": "varchar"
					},
					{
						"name": "AHStopResponse",
						"type": "varchar"
					},
					{
						"name": "AHOthersResponse",
						"type": "varchar"
					},
					{
						"name": "Notes",
						"type": "varchar"
					},
					{
						"name": "BusinessHourContactInfo",
						"type": "varchar"
					},
					{
						"name": "BHSiteContact",
						"type": "varchar"
					},
					{
						"name": "BHContactPhone1",
						"type": "varchar"
					},
					{
						"name": "BHContactMobile",
						"type": "varchar"
					},
					{
						"name": "BHContactRoleViewId",
						"type": "varchar"
					},
					{
						"name": "BHContactRoleName",
						"type": "varchar"
					},
					{
						"name": "AfterHourContactInfo",
						"type": "varchar"
					},
					{
						"name": "AHSiteContact",
						"type": "varchar"
					},
					{
						"name": "AHContactPhone1",
						"type": "varchar"
					},
					{
						"name": "AHContactMobile",
						"type": "varchar"
					},
					{
						"name": "AHContactRoleViewId",
						"type": "varchar"
					},
					{
						"name": "AHContactRoleViewName",
						"type": "varchar"
					},
					{
						"name": "State",
						"type": "varchar"
					},
					{
						"name": "ViewId",
						"type": "varchar"
					},
					{
						"name": "Name",
						"type": "varchar"
					},
					{
						"name": "TimeZone",
						"type": "varchar"
					},
					{
						"name": "CustomerCode",
						"type": "varchar"
					}
				],
				"typeProperties": {
					"schema": "dbo",
					"table": "building stg"
				}
			},
			"dependsOn": []
		},
		{
			"name": "[concat(parameters('factoryName'), '/contactpontex')]",
			"type": "Microsoft.DataFactory/factories/datasets",
			"apiVersion": "2018-06-01",
			"properties": {
				"linkedServiceName": {
					"referenceName": "AzureBlobStorage1",
					"type": "LinkedServiceReference"
				},
				"annotations": [],
				"type": "Excel",
				"typeProperties": {
					"sheetName": "Sheet1",
					"location": {
						"type": "AzureBlobStorageLocation",
						"fileName": "ORA_FD02_CustomerContactPoints20201005174313.xlsx",
						"container": "customercontactpoints"
					},
					"firstRowAsHeader": true
				},
				"schema": [
					{
						"name": "Customer Header Reference",
						"type": "String"
					},
					{
						"name": "Address Reference",
						"type": "String"
					},
					{
						"name": "Contact Point Type",
						"type": "String"
					},
					{
						"name": "Contact Point Status",
						"type": "String"
					},
					{
						"name": "Primary Flag",
						"type": "String"
					},
					{
						"name": "Contact point Purpose",
						"type": "String"
					},
					{
						"name": "Phone Country Code",
						"type": "String"
					},
					{
						"name": "Phone Area Code",
						"type": "String"
					},
					{
						"name": "Phone Number",
						"type": "String"
					},
					{
						"name": "Phone Extension",
						"type": "String"
					},
					{
						"name": "Phone Line Type",
						"type": "String"
					},
					{
						"name": "Email Address",
						"type": "String"
					},
					{
						"name": "Email Format",
						"type": "String"
					},
					{
						"name": "Operating Unit Name",
						"type": "String"
					}
				]
			},
			"dependsOn": []
		},
		{
			"name": "[concat(parameters('factoryName'), '/customerBuilding1')]",
			"type": "Microsoft.DataFactory/factories/datasets",
			"apiVersion": "2018-06-01",
			"properties": {
				"linkedServiceName": {
					"referenceName": "AzureSqlDatabase1",
					"type": "LinkedServiceReference"
				},
				"annotations": [],
				"type": "AzureSqlTable",
				"schema": [
					{
						"name": "ExternalBuildingId",
						"type": "varchar"
					},
					{
						"name": "BuildingName_local",
						"type": "varchar"
					},
					{
						"name": "StreetAddress_Local",
						"type": "varchar"
					},
					{
						"name": "City_Local",
						"type": "varchar"
					},
					{
						"name": "Postcode",
						"type": "varchar"
					},
					{
						"name": "MainTypeViewId",
						"type": "varchar"
					},
					{
						"name": "MainTypeName_En",
						"type": "varchar"
					},
					{
						"name": "SubTypeViewId",
						"type": "varchar"
					},
					{
						"name": "SubTypeName_En",
						"type": "varchar"
					},
					{
						"name": "BuildingNo",
						"type": "varchar"
					},
					{
						"name": "CustomerNo",
						"type": "varchar"
					},
					{
						"name": "SumOfTotalUnits",
						"type": "varchar"
					},
					{
						"name": "SumOfUnitsInService",
						"type": "varchar"
					},
					{
						"name": "OfficeViewId",
						"type": "varchar"
					},
					{
						"name": "OfficeName_En",
						"type": "varchar"
					},
					{
						"name": "UnitsScheduleHours",
						"type": "varchar"
					},
					{
						"name": "UnitsScheduleHoursViewId",
						"type": "varchar"
					},
					{
						"name": "UnitsScheduleTime",
						"type": "varchar"
					},
					{
						"name": "UnitsScheduleTimeViewId",
						"type": "varchar"
					},
					{
						"name": "TargetCallRate",
						"type": "varchar"
					},
					{
						"name": "RunInfo",
						"type": "varchar"
					},
					{
						"name": "RunTypeViewId",
						"type": "varchar"
					},
					{
						"name": "RunTypeName",
						"type": "varchar"
					},
					{
						"name": "RunViewId",
						"type": "varchar"
					},
					{
						"name": "RunName",
						"type": "varchar"
					},
					{
						"name": "BHSWPResponse",
						"type": "varchar"
					},
					{
						"name": "BHStopResponse",
						"type": "varchar"
					},
					{
						"name": "BHOthersResponse",
						"type": "varchar"
					},
					{
						"name": "AHSWPResponse",
						"type": "varchar"
					},
					{
						"name": "AHStopResponse",
						"type": "varchar"
					},
					{
						"name": "AHOthersResponse",
						"type": "varchar"
					},
					{
						"name": "Notes",
						"type": "varchar"
					},
					{
						"name": "BusinessHourContactInfo",
						"type": "varchar"
					},
					{
						"name": "BHSiteContact",
						"type": "varchar"
					},
					{
						"name": "BHContactPhone1",
						"type": "varchar"
					},
					{
						"name": "BHContactMobile",
						"type": "varchar"
					},
					{
						"name": "BHContactRoleViewId",
						"type": "varchar"
					},
					{
						"name": "BHContactRoleName",
						"type": "varchar"
					},
					{
						"name": "AfterHourContactInfo",
						"type": "varchar"
					},
					{
						"name": "AHSiteContact",
						"type": "varchar"
					},
					{
						"name": "AHContactPhone1",
						"type": "varchar"
					},
					{
						"name": "AHContactMobile",
						"type": "varchar"
					},
					{
						"name": "AHContactRoleViewId",
						"type": "varchar"
					},
					{
						"name": "AHContactRoleViewName",
						"type": "varchar"
					},
					{
						"name": "State",
						"type": "varchar"
					},
					{
						"name": "ViewId",
						"type": "varchar"
					},
					{
						"name": "Name",
						"type": "varchar"
					},
					{
						"name": "TimeZone",
						"type": "varchar"
					},
					{
						"name": "CustomerCode",
						"type": "varchar"
					},
					{
						"name": "LastModifytime",
						"type": "timestamp"
					}
				],
				"typeProperties": {
					"schema": "customer",
					"table": "Building1"
				}
			},
			"dependsOn": []
		}
	]
}